wyn_voicebot/__init__.py
wyn_voicebot/voicebot.py
wyn_voicebot-0.1.5.dist-info/METADATA
wyn_voicebot-0.1.5.dist-info/WHEEL
wyn_voicebot-0.1.5.dist-info/RECORD
