Metadata-Version: 2.1
Name: wyn-voicebot
Version: 0.1.5
Summary: This library provides audio interface with OpenAI endpoint.
Author: Yiqiao Yin
Author-email: eagle0504@gmail.com
Requires-Python: >=3.9,<4.0
Classifier: Programming Language :: Python :: 3
Classifier: Programming Language :: Python :: 3.9
Classifier: Programming Language :: Python :: 3.10
Classifier: Programming Language :: Python :: 3.11
Classifier: Programming Language :: Python :: 3.12
Requires-Dist: google-colab (>=1.0.0,<2.0.0)
Requires-Dist: ipython (>=5.5.0,<6.0.0)
Requires-Dist: openai (>=1.35.14,<2.0.0)
